[
  {
    "clientname": "7ELEVEN",
    "storenumber": 841,
    "storename": "UNITED PARANAQUE",
    "zone": "L4 D4 A11",
    "storetype": "CO",
    "contactnumber": 9491255294,
    "storeemail": "st841@store.philseven.com",
    "address": "LOT 2 BLOCK 1 KM 15 IBA STREET TINDALO STREET SAN MARTIN DE PORES UNITED PARANAQUE 2 PARAAÑAQUE CITY, SAN DIONISIO, PARAAÑAQUE, PHILIPPINES",
    "googlemapaddress": "https://www.7-eleven.com.ph/store-locator/",
    "createdby": "",
    "createddate": ""
  }
]